<Stats deaths="1" kills="23" player_kills="1" player_projectile_count="0" >
  <death_map>
    <E key="player | $damage_explosion" value="1" >
    </E>
  </death_map>
  <kill_map>
    <E key="firebug" value="1" >
    </E>
    <E key="longleg" value="5" >
    </E>
    <E key="miner_weak" value="2" >
    </E>
    <E key="player" value="1" >
    </E>
    <E key="rat" value="1" >
    </E>
    <E key="shotgunner" value="1" >
    </E>
    <E key="shotgunner_weak" value="4" >
    </E>
    <E key="slimeshooter_weak" value="2" >
    </E>
    <E key="tnt" value="1" >
    </E>
    <E key="worm_tiny" value="1" >
    </E>
    <E key="zombie_weak" value="4" >
    </E>
  </kill_map>
</Stats>
